<?xml version="1.0" encoding="utf-8"?>
<content>
    <_L_i>
        <id>_L_i</id>
        <position>
            <x>0</x>
            <y>0</y>
        </position>
        <delay>0</delay>
        <rules>2a/2a-&gt;a;0 a/a-&gt;0;0</rules>
        <spikes>0</spikes>
        <out>_L_i1</out>
        <out>_r</out>
        <out>_L_i2</out>
        <outWeights>
            <_L_i1>1</_L_i1>
            <_r>1</_r>
            <_L_i2>1</_L_i2>
        </outWeights>
    </_L_i>
    <_L_i1>
        <id>_L_i1</id>
        <position>
            <x>0</x>
            <y>0</y>
        </position>
        <delay>0</delay>
        <rules>a/a-&gt;a;0</rules>
        <spikes>1</spikes>
        <out>_L_j</out>
        <outWeights>
            <_L_j>1</_L_j>
        </outWeights>
    </_L_i1>
    <_L_i2>
        <id>_L_i2</id>
        <position>
            <x>0</x>
            <y>0</y>
        </position>
        <delay>0</delay>
        <rules>a/a-&gt;a;1</rules>
        <spikes>1</spikes>
        <out>_L_k</out>
        <outWeights>
            <_L_k>1</_L_k>
        </outWeights>
    </_L_i2>
    <_L_j>
        <id>_L_j</id>
        <position>
            <x>0</x>
            <y>0</y>
        </position>
        <delay>0</delay>
        <rules>2a/2a-&gt;a;0 a/a-&gt;0;0</rules>
        <spikes>0</spikes>
    </_L_j>
    <_L_k>
        <id>_L_k</id>
        <position>
            <x>0</x>
            <y>0</y>
        </position>
        <delay>0</delay>
        <rules>2a/2a-&gt;a;0 a/a-&gt;0;0</rules>
        <spikes>0</spikes>
    </_L_k>
    <_r>
        <id>_r</id>
        <position>
            <x>0</x>
            <y>0</y>
        </position>
        <delay>0</delay>
        <rules>a(aa)+/3a-&gt;a;0 a/a-&gt;a;1</rules>
        <spikes>301</spikes>
        <out>_L_j</out>
        <out>_L_k</out>
        <outWeights>
            <_L_j>1</_L_j>
            <_L_k>1</_L_k>
        </outWeights>
    </_r>
</content>